tableexec/__main__.py
tableexec-0.0.4.dist-info/METADATA
tableexec-0.0.4.dist-info/WHEEL
tableexec-0.0.4.dist-info/entry_points.txt
tableexec-0.0.4.dist-info/top_level.txt
tableexec-0.0.4.dist-info/RECORD
