Metadata-Version: 2.4
Name: tableexec
Version: 0.0.4
Summary: Execute command for every row in Excel/ODS table.
Home-page: https://github.com/fantastic001/tableexec
Download-URL: https://github.com/fantastic001/tableexec/tarball/0.0.1
Author: Stefan Nožinić
Author-email: stefan@lugons.org
Keywords: excel,spreadsheet
Requires-Dist: pandas
Requires-Dist: odfpy
Requires-Dist: xlrd
Dynamic: author
Dynamic: author-email
Dynamic: download-url
Dynamic: home-page
Dynamic: keywords
Dynamic: requires-dist
Dynamic: summary
